{
  "generated_at": "2026-04-20T06:26:49.616051+00:00",
  "symbol": "SOLUSDT",
  "exchange": "Binance Margin",
  "price": 83.98,
  "usdt_balance": 59.14919329,
  "leverage": 5.0,
  "trade_amount": 40.0,
  "position": null,
  "active_qty": null,
  "trade_opened_at": null,
  "action": "HOLD",
  "confidence": 0,
  "status": "HOLD \u2014 BEARISH \u2014 waiting for EMA21 bounce: candle high $84.04000 not near EMA21 $84.74423",
  "bot_paused": false,
  "regime": "TRENDING",
  "trend_direction": "BEARISH",
  "reason": "BEARISH \u2014 waiting for EMA21 bounce: candle high $84.04000 not near EMA21 $84.74423",
  "indicators": {
    "adx": 30.23,
    "adx_pos": 16.23,
    "adx_neg": 29.95,
    "ema21": 84.74423,
    "ema50": 85.593498,
    "rsi": 38.3,
    "atr": 0.663676
  },
  "closed_trades": [],
  "performance": {
    "closed_trades": 0,
    "wins": 0,
    "losses": 0,
    "win_rate": 0.0,
    "net_profit": 0,
    "avg_pnl": 0.0,
    "best_trade": 0.0,
    "worst_trade": 0.0
  },
  "trail": {
    "entry_price": null,
    "best_price": null,
    "atr": null,
    "sl": null,
    "trail_stop": null,
    "active": false
  },
  "run_count": 3
}